[
  {
    "full_name": "lens-protocol/core",
    "stargazers_count": 1876,
    "open_issues_count": 22,
    "forks_count": 418
  },
  {
    "full_name": "CryptoNifters/lens-protocol",
    "stargazers_count": 1,
    "open_issues_count": 0,
    "forks_count": 0
  },
  {
    "full_name": "eth-brownie/brownie",
    "stargazers_count": 2445,
    "open_issues_count": 406,
    "forks_count": 523
  },
  {
    "full_name": "open-sauced/open-sauced",
    "stargazers_count": 881,
    "open_issues_count": 8,
    "forks_count": 625
  }
]